{"chunk":7,"numChunks":110,"fileHash":"7wNDjkOqo5xcEE0RTrtFd8kUcfFt7BWSQhaTiClT1+o=","filePath":"public/ui.js","content":"import { state } from './state.js';\nexport function showEntityView(nodeId) {\n    if (hasError) {\n    } else if (hasTaintOnly) {\n        if (risk >= 70) {\n            accentColor='#b45309'; accentBg='#fffbeb'; accentLabel='HIGH TAINT RISK'; accentIcon='⚠️';\n            accentGlow='box-shadow:0 0 20px rgba(245,158,11,0.2)';\n        } else if (risk >= 40) {\n            accentColor='#92400e'; accentBg='#fefce8'; accentLabel='ELEVATED TAINT RISK'; accentIcon='⚠️'; accentGlow='';\n        } else {\n            accentColor='#374151'; accentBg='#f8fafc'; accentLabel='LOW TAINT RISK'; accentIcon='🔗'; accentGlow='';\n        }\n    } else if (!hasReports && risk === 0) {"}