{"chunk":177,"numChunks":198,"fileHash":"w4jhtI3rJrndRARjiRECc4GAf6rhZPv9nGjH6Ls9mZ0=","filePath":"public/graph.js","content":"import { state } from './state.js';\nexport async function mergePathIntoGraph(path) {\n    for (let idx = 0; idx < total; idx++) {\n        const hop = path.hops[idx];\n        setBusy(true,\n            'TRACING PATH… HOP ' + (idx + 1) + ' / ' + total,\n            '\\u2192 ' + (hop.to_addr.length > 28 ? hop.to_addr.substring(0, 14) + '\\u2026' + hop.to_addr.slice(-10) : hop.to_addr)\n        );\n        // Spread hops in a slight arc to avoid overlap\n        const angle  = (idx - (total - 1) / 2) * 0.3; // radians\n        const txX    = prevX + STEP_X * Math.cos(angle);\n        const txY    = prevY + STEP_X * Math.sin(angle) * 0.5;\n        const toX    = prevX + STEP_X * 1.9 * Math.cos(angle);\n        const toY    = prevY + STEP_X * 1.9 * Math.sin(angle) * 0.5;\n        // Add TX node\n        if (!existingNodeIds.has(hop.tx_hash)) {\n            rawNodes.push({\n                id: hop.tx_hash, label: hop.tx_hash, type: 'Transaction',\n                sources: ['Trace'], risk: 0, isTarget: false, x: txX, y: txY\n            });\n            fullGraphData.nodes[hop.tx_hash] = { label: hop.tx_hash, type: 'Transaction', sources: ['Trace'], risk: 0 };\n            existingNodeIds.add(hop.tx_hash);\n        }\n        tracePathNodeIds.add(hop.tx_hash);\n        // Add destination address node"}