{"chunk":26,"numChunks":50,"fileHash":"NADHuyXHjh1yJpB2gWL57uylU/zreNnsnsTl7AXuK5E=","filePath":"internal/aggregator/aggregator.go","content":"package aggregator\nfunc IsExchangeAddress(txs []TransactionIO, threshold float64) ExchangeResult {\n\tif len(txs) > 1 {\n\t\ttimestamps := make([]int64, 0, len(txs))\n\t\tfor _, tx := range txs {\n\t\t\tif tx.Timestamp > 0 {\n\t\t\t\ttimestamps = append(timestamps, tx.Timestamp)\n\t\t\t}\n\t\t}\n\t\tsort.Slice(timestamps, func(i, j int) bool { return timestamps[i] < timestamps[j] })\n\t\tif len(timestamps) >= 2 {\n\t\t\tspan := time.Duration(timestamps[len(timestamps)-1]-timestamps[0]) * time.Second\n\t\t\ttxPerDay := float64(len(timestamps)) / math.Max(span.Hours()/24, 1)\n\t\t\tif txPerDay > 50 {\n\t\t\t\tscore := math.Min(txPerDay/500, 1.0)\n\t\t\t\tresult.Breakdown[\"high_frequency\"] = 0.20 * score\n\t\t\t\tresult.Notes = append(result.Notes, fmt.Sprintf(\n\t\t\t\t\t\"%.1f transactions/day\", txPerDay))\n\t\t\t}\n\t\t}\n\t}\n\n\t// RULE 3: Fan-Out Pattern (0.20)\n\tfanOutCount := 0\n\tallOutputAddrs := make(map[string]struct{})\n\tfor _, tx := range txs {\n\t\tif len(tx.Outputs) >= 5 {\n\t\t\tfanOutCount++\n\t\t}\n\t\tfor _, o := range tx.Outputs {\n\t\t\tallOutputAddrs[o.Address] = struct{}{}\n\t\t}\n\t}\n\tfanOutRatio := float64(fanOutCount) / float64(len(txs))"}