{"chunk":92,"numChunks":194,"fileHash":"X5e4+92p1J2WkzNXe1vu4nF6bctn8lXwcBDj1eZ6Nw0=","filePath":"public/graph.js","content":"import { state } from './state.js';\nasync function expandAll() {\n    for (const nodeId of queue) {\n        if (!expandedNodes.has(nodeId)) {\n            try {\n                if (data.graph?.nodes) {\n                    const anchor = rawNodes.find(n => n.id === nodeId);\n                    const ax = anchor?.x ?? 0, ay = anchor?.y ?? 0;\n                    const existingIds  = new Set(rawNodes.map(n => n.id));\n                    const existingKeys = new Set(rawLinks.map(l =>\n                        `${l.source?.id || l.source}|${l.target?.id || l.target}`));\n                    Object.entries(data.graph.nodes).forEach(([id, n]) => {\n                        if (existingIds.has(id)) return;\n                        const angle = Math.random() * 2 * Math.PI;\n                        const dist  = 80 + Math.random() * 80;\n                        rawNodes.push({ id, ...n, label: n.label || id, isTarget: false,\n                            x: ax + Math.cos(angle) * dist, y: ay + Math.sin(angle) * dist });\n                        fullGraphData.nodes[id] = n;\n                    });\n                    (data.graph.edges || []).forEach(e => {\n                        if (existingKeys.has(`${e.source}|${e.target}`)) return;\n                        rawLinks.push({ ...e });\n                        if (!fullGraphData.edges) fullGraphData.edges = [];\n                        fullGraphData.edges.push(e);\n                    });\n                    rebindGraphSelections();\n                    updateExpandRings();\n                    document.getElementById('nodeCount').textContent = rawNodes.length.toLocaleString();\n                    document.getElementById('edgeCount').textContent = rawLinks.length.toLocaleString();\n                    if (simulation) simulation.stop();"}